nonebot_plugin_russian_ban/__init__.py
nonebot_plugin_russian_ban/utils.py
nonebot_plugin_russian_ban-1.1.0.post1.dist-info/LICENSE
nonebot_plugin_russian_ban-1.1.0.post1.dist-info/METADATA
nonebot_plugin_russian_ban-1.1.0.post1.dist-info/WHEEL
nonebot_plugin_russian_ban-1.1.0.post1.dist-info/RECORD
