Metadata-Version: 2.3
Name: nonebot-plugin-russian-ban
Version: 1.1.0.post1
Summary: 
Author: KarisAya
Author-email: karisaya@foxmail.com
Requires-Python: >=3.12,<4.0.0
Classifier: Programming Language :: Python :: 3
Classifier: Programming Language :: Python :: 3.12
Classifier: Programming Language :: Python :: 3.13
Requires-Dist: nonebot-adapter-onebot (>=2.4.6,<3.0.0)
Requires-Dist: nonebot2 (>=2.4.2,<3.0.0)
